abq.py
kw.py
odbexport/__init__.py
odbexport/export.py
odbexport/odbfunc.py
abaqustools-2.34.dist-info/LICENSE
abaqustools-2.34.dist-info/METADATA
abaqustools-2.34.dist-info/WHEEL
abaqustools-2.34.dist-info/top_level.txt
abaqustools-2.34.dist-info/RECORD
